{"info": {"address1": "925 North Eldridge Parkway", "city": "Houston", "state": "TX", "zip": "77079-2703", "country": "United States", "phone": "281 293 1000", "website": "https://www.conocophillips.com", "industry": "Oil & Gas E&P", "sector": "Energy", "longBusinessSummary": "ConocoPhillips explores for, produces, transports, and markets crude oil, bitumen, natural gas, liquefied natural gas (LNG), and natural gas liquids in the United States and internationally. The company's portfolio includes unconventional plays in North America; conventional assets in North America, Europe, Asia, and Australia; various LNG developments; oil sands assets in Canada; and an inventory of global exploration prospects. ConocoPhillips was founded in 1917 and is headquartered in Houston, Texas.", "fullTimeEmployees": 9500, "companyOfficers": [{"maxAge": 1, "name": "Mr. Ryan M. Lance", "age": 60, "title": "Chairman & CEO", "yearBorn": 1962, "fiscalYear": 2022, "totalPay": 5663471, "exercisedValue": 36928712, "unexercisedValue": 163684432}, {"maxAge": 1, "name": "Mr. William L. Bullock Jr.", "age": 57, "title": "Exec. VP & CFO", "yearBorn": 1965, "fiscalYear": 2022, "totalPay": 2760421, "exercisedValue": 2883681, "unexercisedValue": 13937645}, {"maxAge": 1, "name": "Mr. Dominic E. Macklon", "age": 52, "title": "Exec. VP of Strategy, Sustainability & Technology", "yearBorn": 1970, "fiscalYear": 2022, "totalPay": 1994970, "exercisedValue": 794349, "unexercisedValue": 0}, {"maxAge": 1, "name": "Ms. Kelly Brunetti Rose J.D.", "age": 55, "title": "Sr. VP of Legal & Gen. Counsel", "yearBorn": 1967, "fiscalYear": 2022, "totalPay": 2174272, "exercisedValue": 0, "unexercisedValue": 0}, {"maxAge": 1, "name": "Mr. Nicholas G. Olds", "age": 52, "title": "Exec. VP of Lower 48", "yearBorn": 1970, "fiscalYear": 2022, "totalPay": 1762943, "exercisedValue": 4329892, "unexercisedValue": 1658354}, {"maxAge": 1, "name": "Mr. Timothy A. Leach", "age": 62, "title": "Director & Advisor", "yearBorn": 1960, "fiscalYear": 2022, "totalPay": 2393337, "exercisedValue": 0, "unexercisedValue": 0}, {"maxAge": 1, "name": "Mr. Andrew M. O'Brien", "age": 47, "title": "Sr. VP of Global Operations", "yearBorn": 1975, "exercisedValue": 0, "unexercisedValue": 0}, {"maxAge": 1, "name": "Mr. Mark  Keener", "title": "VP of Investor Relations", "exercisedValue": 0, "unexercisedValue": 0}, {"maxAge": 1, "name": "Shannon B. Kinney", "title": "Deputy Gen. Counsel, Chief Compliance Officer & Corp. Sec.", "exercisedValue": 0, "unexercisedValue": 0}, {"maxAge": 1, "name": "Ms. Heather G. Sirdashney", "age": 48, "title": "Sr. VP of HR & Real Estate and Facilities Services", "yearBorn": 1974, "exercisedValue": 0, "unexercisedValue": 0}], "auditRisk": 2, "boardRisk": 4, "compensationRisk": 10, "shareHolderRightsRisk": 8, "overallRisk": 9, "governanceEpochDate": 1680307200, "compensationAsOfEpochDate": 1672444800, "maxAge": 86400, "priceHint": 2, "previousClose": 105.61, "open": 104.99, "dayLow": 104.095, "dayHigh": 105.7, "regularMarketPreviousClose": 105.61, "regularMarketOpen": 104.99, "regularMarketDayLow": 104.095, "regularMarketDayHigh": 105.7, "dividendRate": 2.32, "dividendYield": 0.0221, "exDividendDate": 1679961600, "payoutRatio": 0.2464, "fiveYearAvgDividendYield": 2.51, "beta": 1.320069, "trailingPE": 7.203157, "forwardPE": 9.584475, "volume": 7740303, "regularMarketVolume": 7740303, "averageVolume": 7053231, "averageVolume10days": 5984710, "averageDailyVolume10Day": 5984710, "bid": 103.52, "ask": 107.0, "bidSize": 800, "askSize": 800, "marketCap": 127186796544, "fiftyTwoWeekLow": 78.3, "fiftyTwoWeekHigh": 138.49, "priceToSalesTrailing12Months": 1.5784897, "fiftyDayAverage": 104.7418, "twoHundredDayAverage": 110.0145, "trailingAnnualDividendRate": 4.49, "trailingAnnualDividendYield": 0.042514913, "currency": "USD", "enterpriseValue": 135855595520, "profitMargins": 0.23183, "floatShares": 1216948329, "sharesOutstanding": 1211879936, "sharesShort": 10841811, "sharesShortPriorMonth": 12238666, "sharesShortPreviousMonthDate": 1677542400, "dateShortInterest": 1680220800, "sharesPercentSharesOut": 0.0089, "heldPercentInsiders": 0.0013799999, "heldPercentInstitutions": 0.82935995, "shortRatio": 1.51, "shortPercentOfFloat": 0.009, "impliedSharesOutstanding": 0, "bookValue": 39.223, "priceToBook": 2.675726, "lastFiscalYearEnd": 1672444800, "nextFiscalYearEnd": 1703980800, "mostRecentQuarter": 1672444800, "earningsQuarterlyGrowth": 0.237, "netIncomeToCommon": 18620000256, "trailingEps": 14.57, "forwardEps": 10.95, "pegRatio": -1.05, "lastSplitFactor": "1311791:1000000", "lastSplitDate": 1335830400, "enterpriseToRevenue": 1.686, "enterpriseToEbitda": 3.894, "52WeekChange": 0.022207022, "SandP52WeekChange": -0.06829989, "lastDividendValue": 0.6, "lastDividendDate": 1679961600, "exchange": "NYQ", "quoteType": "EQUITY", "symbol": "COP", "underlyingSymbol": "COP", "shortName": "ConocoPhillips", "longName": "ConocoPhillips", "firstTradeDateEpochUtc": 378657000, "timeZoneFullName": "America/New_York", "timeZoneShortName": "EDT", "uuid": "97afc5c1-9a02-314c-bde1-c064281437c5", "messageBoardId": "finmb_296527", "gmtOffSetMilliseconds": -14400000, "currentPrice": 104.95, "targetHighPrice": 167.0, "targetLowPrice": 92.0, "targetMeanPrice": 131.29, "targetMedianPrice": 134.5, "recommendationMean": 2.1, "recommendationKey": "buy", "numberOfAnalystOpinions": 24, "totalCash": 9242999808, "totalCashPerShare": 7.584, "ebitda": 34884001792, "totalDebt": 17187999744, "quickRatio": 1.271, "currentRatio": 1.459, "totalRevenue": 80574996480, "debtToEquity": 35.806, "revenuePerShare": 63.244, "returnOnAssets": 0.18491, "returnOnEquity": 0.39995998, "grossProfits": 39598000000, "freeCashflow": 15959749632, "operatingCashflow": 28313999360, "earningsGrowth": 0.298, "revenueGrowth": 0.238, "grossMargins": 0.49144, "ebitdaMargins": 0.43293998, "operatingMargins": 0.3387, "financialCurrency": "USD", "trailingPegRatio": 0.8099}, "news": [{"uuid": "2a993eed-b2eb-3d65-9717-a8e0f2ffee89", "title": "The Zacks Analyst Blog Highlights NIKE, Toyota Motor, ConocoPhillips, PayPal and Zoetis", "publisher": "Zacks", "link": "https://finance.yahoo.com/news/zacks-analyst-blog-highlights-nike-132701499.html", "providerPublishTime": 1681824421, "type": "STORY", "thumbnail": {"resolutions": [{"url": "https://s.yimg.com/uu/api/res/1.2/LzMZuwUbXggoIF0s8sNy8A--~B/aD00MDA7dz02MzU7YXBwaWQ9eXRhY2h5b24-/https://media.zenfs.com/en/zacks.com/49d99af140c116ba99c496e1d63a0d38", "width": 635, "height": 400, "tag": "original"}, {"url": "https://s.yimg.com/uu/api/res/1.2/CAcZhTBdd9lUFYsXqLRfQw--~B/Zmk9ZmlsbDtoPTE0MDtweW9mZj0wO3c9MTQwO2FwcGlkPXl0YWNoeW9u/https://media.zenfs.com/en/zacks.com/49d99af140c116ba99c496e1d63a0d38", "width": 140, "height": 140, "tag": "140x140"}]}, "relatedTickers": ["COP", "NKE", "TM", "ZTS"]}, {"uuid": "ed04d273-120f-3664-9e4a-031cb02dc632", "title": "Q1 Earnings Scorecard and Analyst Reports for NIKE, Toyota Motor & ConocoPhillips", "publisher": "Zacks", "link": "https://finance.yahoo.com/news/q1-earnings-scorecard-analyst-reports-204908208.html", "providerPublishTime": 1681764548, "type": "STORY", "thumbnail": {"resolutions": [{"url": "https://s.yimg.com/uu/api/res/1.2/DBRXpVRmG1p_UwNhFB9dZg--~B/aD00NzY7dz05MDA7YXBwaWQ9eXRhY2h5b24-/https://media.zenfs.com/en/zacks.com/c57dbafbfe115dbdb95d6f312af81f7e", "width": 900, "height": 476, "tag": "original"}, {"url": "https://s.yimg.com/uu/api/res/1.2/7V3XSdwZaIp0bEX8ULBS.g--~B/Zmk9ZmlsbDtoPTE0MDtweW9mZj0wO3c9MTQwO2FwcGlkPXl0YWNoeW9u/https://media.zenfs.com/en/zacks.com/c57dbafbfe115dbdb95d6f312af81f7e", "width": 140, "height": 140, "tag": "140x140"}]}, "relatedTickers": ["COP", "TM", "NKE", "PYPL", "ZTS"]}, {"uuid": "28de3048-8257-3c55-808d-5a6d7ab6e674", "title": "Rob Arnott Says It\u2019s Time to Buy Into Value Stocks; Here Are 2 Names That Analysts Like", "publisher": "TipRanks", "link": "https://finance.yahoo.com/news/rob-arnott-says-time-buy-233751545.html", "providerPublishTime": 1681688271, "type": "STORY", "thumbnail": {"resolutions": [{"url": "https://s.yimg.com/uu/api/res/1.2/PK1euJ4OQ9qIkJntC8.Wjg--~B/aD01ODY7dz05MTg7YXBwaWQ9eXRhY2h5b24-/https://media.zenfs.com/en/tipranks_452/8dd995ca3ee27d1481e9b79b1711c4ce", "width": 918, "height": 586, "tag": "original"}, {"url": "https://s.yimg.com/uu/api/res/1.2/emtTqYKz.DCJgGtovMBi1A--~B/Zmk9ZmlsbDtoPTE0MDtweW9mZj0wO3c9MTQwO2FwcGlkPXl0YWNoeW9u/https://media.zenfs.com/en/tipranks_452/8dd995ca3ee27d1481e9b79b1711c4ce", "width": 140, "height": 140, "tag": "140x140"}]}, "relatedTickers": ["UNH", "COP"]}, {"uuid": "34291fde-06db-31bc-b73e-2d5e49b5b646", "title": "ConocoPhillips (COP) Outpaces Stock Market Gains: What You Should Know", "publisher": "Zacks", "link": "https://finance.yahoo.com/news/conocophillips-cop-outpaces-stock-market-214509996.html", "providerPublishTime": 1681422309, "type": "STORY", "thumbnail": {"resolutions": [{"url": "https://s.yimg.com/uu/api/res/1.2/d6hN0_BhikrNdWTnix6fng--~B/aD03NDE7dz05MDA7YXBwaWQ9eXRhY2h5b24-/https://media.zenfs.com/en/zacks.com/7853de8d69faeccb7d1ad6ebba40b8a2", "width": 900, "height": 741, "tag": "original"}, {"url": "https://s.yimg.com/uu/api/res/1.2/fK_ZnUjpgS53xdJHns_S2A--~B/Zmk9ZmlsbDtoPTE0MDtweW9mZj0wO3c9MTQwO2FwcGlkPXl0YWNoeW9u/https://media.zenfs.com/en/zacks.com/7853de8d69faeccb7d1ad6ebba40b8a2", "width": 140, "height": 140, "tag": "140x140"}]}, "relatedTickers": ["COP"]}, {"uuid": "7950927c-2b68-3353-a223-6e3d7fa0db45", "title": "This Oil Stock Could Send $100+ Billion Back to Investors Over the Next Decade", "publisher": "Motley Fool", "link": "https://finance.yahoo.com/m/7950927c-2b68-3353-a223-6e3d7fa0db45/this-oil-stock-could-send.html", "providerPublishTime": 1681388760, "type": "STORY", "thumbnail": {"resolutions": [{"url": "https://s.yimg.com/uu/api/res/1.2/7F3dXlOnexfGUZq8GpS4CA--~B/aD0xNDE0O3c9MjEyMTthcHBpZD15dGFjaHlvbg--/https://media.zenfs.com/en/motleyfool.com/58ec545c13f672f89ad017a3a38370b8", "width": 2121, "height": 1414, "tag": "original"}, {"url": "https://s.yimg.com/uu/api/res/1.2/k5ANxCisyqVerkguyYcteQ--~B/Zmk9ZmlsbDtoPTE0MDtweW9mZj0wO3c9MTQwO2FwcGlkPXl0YWNoeW9u/https://media.zenfs.com/en/motleyfool.com/58ec545c13f672f89ad017a3a38370b8", "width": 140, "height": 140, "tag": "140x140"}]}, "relatedTickers": ["COP"]}, {"uuid": "c4232af0-10ab-3b33-bd15-4947e5573ad2", "title": "Should You Buy ConocoPhillips (COP) Now?", "publisher": "Insider Monkey", "link": "https://finance.yahoo.com/news/buy-conocophillips-cop-now-122144938.html", "providerPublishTime": 1681388504, "type": "STORY", "thumbnail": {"resolutions": [{"url": "https://s.yimg.com/uu/api/res/1.2/ATDQDh_SKxiYVeVy1IpTPA--~B/aD0xNjczO3c9MjUwNzthcHBpZD15dGFjaHlvbg--/https://media.zenfs.com/en/insidermonkey.com/1fade69f4243922ce00b48742a1e6445", "width": 2507, "height": 1673, "tag": "original"}, {"url": "https://s.yimg.com/uu/api/res/1.2/6OpPS8dWV5xWjqBI.mltzw--~B/Zmk9ZmlsbDtoPTE0MDtweW9mZj0wO3c9MTQwO2FwcGlkPXl0YWNoeW9u/https://media.zenfs.com/en/insidermonkey.com/1fade69f4243922ce00b48742a1e6445", "width": 140, "height": 140, "tag": "140x140"}]}, "relatedTickers": ["COP"]}, {"uuid": "6817779d-0858-3943-9279-dd5e8d43e114", "title": "Biden hasn\u2019t changed on fossil fuels, says ConocoPhillips boss", "publisher": "Financial Times", "link": "https://finance.yahoo.com/m/6817779d-0858-3943-9279-dd5e8d43e114/biden-hasn%E2%80%99t-changed-on.html", "providerPublishTime": 1681385431, "type": "STORY", "relatedTickers": ["COP"]}, {"uuid": "b24a0685-5223-3725-b8df-b5e2763dfeb7", "title": "7 Oil Stocks to Buy for the Spring Surge", "publisher": "InvestorPlace", "link": "https://finance.yahoo.com/news/7-oil-stocks-buy-spring-103025852.html", "providerPublishTime": 1681381825, "type": "STORY", "thumbnail": {"resolutions": [{"url": "https://s.yimg.com/uu/api/res/1.2/snI4jpsdYsEOedrCYQGHBA--~B/aD00MDA7dz03Mjg7YXBwaWQ9eXRhY2h5b24-/https://media.zenfs.com/en/investorplace_417/165598dc784151be767978f06740a210", "width": 728, "height": 400, "tag": "original"}, {"url": "https://s.yimg.com/uu/api/res/1.2/euxgSQSuInv9_gU7gp0L_A--~B/Zmk9ZmlsbDtoPTE0MDtweW9mZj0wO3c9MTQwO2FwcGlkPXl0YWNoeW9u/https://media.zenfs.com/en/investorplace_417/165598dc784151be767978f06740a210", "width": 140, "height": 140, "tag": "140x140"}]}, "relatedTickers": ["NG=F", "CL=F", "CVX", "COP", "XOM", "OXY", "CLMT", "BP"]}]}