{"info": {"address1": "Building 100", "address2": "207 High Point Drive", "city": "Victor", "state": "NY", "zip": "14564", "country": "United States", "phone": "585 678 7100", "website": "https://www.cbrands.com", "industry": "Beverages\u2014Wineries & Distilleries", "sector": "Consumer Defensive", "longBusinessSummary": "Constellation Brands, Inc., together with its subsidiaries, produces, imports, markets, and sells beer, wine, and spirits in the United States, Canada, Mexico, New Zealand, and Italy. It provides beer primarily under the Corona Extra, Corona Premier, Corona Familiar, Corona Light, Corona Refresca, Corona Hard Seltzer, Modelo Especial, Modelo Negra, Modelo Chelada, Pacifico, and Victoria brands. The company offers wine under the 7 Moons, Cook's California Champagne, Cooper & Thief, Crafters Union, Kim Crawford, Meiomi, Mount Veeder, Ruffino, SIMI, The Dreaming Tree, Charles Smith, The Prisoner Wine Company, Robert Mondavi, My Favorite Neighbor, and Schrader; and spirits under the Casa Noble, Copper & Kings, High West, Mi CAMPO, Nelson's Green Brier, and SVEDKA brands. It provides its products to wholesale distributors, retailers, on-premise locations, and state alcohol beverage control agencies. Constellation Brands, Inc. was founded in 1945 and is headquartered in Victor, New York.", "companyOfficers": [{"maxAge": 1, "name": "Mr. William A. Newlands", "age": 63, "title": "Pres, CEO & Director", "yearBorn": 1959, "fiscalYear": 2022, "totalPay": 5208705, "exercisedValue": 2094350, "unexercisedValue": 3675630}, {"maxAge": 1, "name": "Mr. Garth  Hankinson", "age": 54, "title": "Exec. VP & CFO", "yearBorn": 1968, "fiscalYear": 2022, "totalPay": 2133207, "exercisedValue": 0, "unexercisedValue": 1335778}, {"maxAge": 1, "name": "Mr. Robert L. Hanson", "age": 59, "title": "Exec. VP and Pres of Wine & Spirits Division", "yearBorn": 1963, "fiscalYear": 2022, "totalPay": 2415144, "exercisedValue": 0, "unexercisedValue": 720603}, {"maxAge": 1, "name": "Ash  Mehra", "title": "Chief Data & Information Officer", "exercisedValue": 0, "unexercisedValue": 0}, {"maxAge": 1, "name": "Mr. Joseph  Suarez", "title": "VP of Investor Relations", "exercisedValue": 0, "unexercisedValue": 0}, {"maxAge": 1, "name": "Mr. James O. Bourdeau", "age": 57, "title": "Exec. VP, Chief Legal Officer & Sec.", "yearBorn": 1965, "exercisedValue": 0, "unexercisedValue": 0}, {"maxAge": 1, "name": "Mr. Michael  McGrew", "age": 48, "title": "Exec. VP and Chief Communications, Corp. Social Responsibility & Diversity Officer", "yearBorn": 1974, "exercisedValue": 0, "unexercisedValue": 0}, {"maxAge": 1, "name": "Andrew  Zrike", "title": "VP of Marketing", "exercisedValue": 0, "unexercisedValue": 0}, {"maxAge": 1, "name": "Steve  King", "title": "VP of Corp. Devel.", "exercisedValue": 0, "unexercisedValue": 0}, {"maxAge": 1, "name": "Ms. K. Kristann Carey", "age": 52, "title": "Exec. VP & Chief HR Officer", "yearBorn": 1970, "exercisedValue": 0, "unexercisedValue": 0}], "auditRisk": 10, "boardRisk": 10, "compensationRisk": 2, "shareHolderRightsRisk": 8, "overallRisk": 9, "governanceEpochDate": 1680307200, "compensationAsOfEpochDate": 1672444800, "maxAge": 86400, "priceHint": 2, "previousClose": 229.68, "open": 229.61, "dayLow": 223.52, "dayHigh": 229.73, "regularMarketPreviousClose": 229.68, "regularMarketOpen": 229.61, "regularMarketDayLow": 223.52, "regularMarketDayHigh": 229.73, "dividendRate": 3.56, "dividendYield": 0.0156, "exDividendDate": 1683072000, "fiveYearAvgDividendYield": 1.43, "beta": 1.030103, "forwardPE": 17.288975, "volume": 1153259, "regularMarketVolume": 1153259, "averageVolume": 1197188, "averageVolume10days": 1485610, "averageDailyVolume10Day": 1485610, "bid": 0.0, "ask": 0.0, "bidSize": 800, "askSize": 800, "marketCap": 41957670912, "fiftyTwoWeekLow": 208.12, "fiftyTwoWeekHigh": 261.52, "priceToSalesTrailing12Months": 4.4387436, "fiftyDayAverage": 222.3316, "twoHundredDayAverage": 234.77126, "trailingAnnualDividendRate": 3.2, "trailingAnnualDividendYield": 0.013932428, "currency": "USD", "enterpriseValue": 54885101568, "profitMargins": -0.00751, "floatShares": 164970366, "sharesOutstanding": 184498000, "sharesShort": 2502349, "sharesShortPriorMonth": 2829556, "sharesShortPreviousMonthDate": 1677542400, "dateShortInterest": 1680220800, "sharesPercentSharesOut": 0.0136, "heldPercentInsiders": 0.14453, "heldPercentInstitutions": 0.76071, "shortRatio": 2.36, "shortPercentOfFloat": 0.014099999, "impliedSharesOutstanding": 2248710, "bookValue": 45.752, "priceToBook": 4.969182, "lastFiscalYearEnd": 1677542400, "nextFiscalYearEnd": 1709078400, "mostRecentQuarter": 1677542400, "earningsQuarterlyGrowth": -0.436, "netIncomeToCommon": -71000000, "trailingEps": -0.11, "forwardEps": 13.15, "pegRatio": 2.08, "lastSplitFactor": "2:1", "lastSplitDate": 1116201600, "enterpriseToRevenue": 5.806, "enterpriseToEbitda": 16.64, "52WeekChange": -0.12145454, "SandP52WeekChange": -0.06829989, "lastDividendValue": 0.8, "lastDividendDate": 1675728000, "exchange": "NYQ", "quoteType": "EQUITY", "symbol": "STZ", "underlyingSymbol": "STZ", "shortName": "Constellation Brands, Inc.", "longName": "Constellation Brands, Inc.", "firstTradeDateEpochUtc": 700842600, "timeZoneFullName": "America/New_York", "timeZoneShortName": "EDT", "uuid": "16c070ad-8526-3e04-8ec0-b53f8aecbb2b", "messageBoardId": "finmb_258589", "gmtOffSetMilliseconds": -14400000, "currentPrice": 227.35, "targetHighPrice": 295.0, "targetLowPrice": 216.0, "targetMeanPrice": 258.28, "targetMedianPrice": 264.0, "recommendationMean": 2.0, "recommendationKey": "buy", "numberOfAnalystOpinions": 21, "totalCash": 133500000, "totalCashPerShare": 0.726, "ebitda": 3298299904, "totalDebt": 12461299712, "quickRatio": 0.349, "currentRatio": 1.178, "totalRevenue": 9452600320, "debtToEquity": 142.677, "revenuePerShare": 49.093, "returnOnAssets": 0.07171, "returnOnEquity": -0.0037, "freeCashflow": 900449984, "operatingCashflow": 2756900096, "earningsGrowth": -0.416, "revenueGrowth": -0.05, "grossMargins": 0.5051, "ebitdaMargins": 0.34893, "operatingMargins": 0.30661, "financialCurrency": "USD", "trailingPegRatio": 2.2024}, "news": [{"uuid": "5d48ef8a-a220-3d8c-9521-302912321df6", "title": "Is Constellation Brands Stock a Buy?", "publisher": "Motley Fool", "link": "https://finance.yahoo.com/m/5d48ef8a-a220-3d8c-9521-302912321df6/is-constellation-brands-stock.html", "providerPublishTime": 1681652700, "type": "STORY", "thumbnail": {"resolutions": [{"url": "https://s.yimg.com/uu/api/res/1.2/zKWqy8DWfyo_bDbjpKTBAA--~B/aD00NjU7dz03MjA7YXBwaWQ9eXRhY2h5b24-/https://media.zenfs.com/en/motleyfool.com/1eb70e776cd766b52a2b320ad10edecd", "width": 720, "height": 465, "tag": "original"}, {"url": "https://s.yimg.com/uu/api/res/1.2/mUqdk38Ypq3c18uyrttb8g--~B/Zmk9ZmlsbDtoPTE0MDtweW9mZj0wO3c9MTQwO2FwcGlkPXl0YWNoeW9u/https://media.zenfs.com/en/motleyfool.com/1eb70e776cd766b52a2b320ad10edecd", "width": 140, "height": 140, "tag": "140x140"}]}, "relatedTickers": ["STZ"]}, {"uuid": "10cc0159-41e7-32cc-baf5-a792f917d6fb", "title": "Estimating The Intrinsic Value Of Constellation Brands, Inc. (NYSE:STZ)", "publisher": "Simply Wall St.", "link": "https://finance.yahoo.com/news/estimating-intrinsic-value-constellation-brands-144508123.html", "providerPublishTime": 1681569908, "type": "STORY", "thumbnail": {"resolutions": [{"url": "https://s.yimg.com/uu/api/res/1.2/KY2Q5F5VhKsl6kikegapyw--~B/aD00MzI7dz0xMTk0O2FwcGlkPXl0YWNoeW9u/https://media.zenfs.com/en/simply_wall_st__316/a2df42ed0a47d9732f3bf156a253b2f7", "width": 1194, "height": 432, "tag": "original"}, {"url": "https://s.yimg.com/uu/api/res/1.2/O.u9FVAvXOlWe_ct7v6DlQ--~B/Zmk9ZmlsbDtoPTE0MDtweW9mZj0wO3c9MTQwO2FwcGlkPXl0YWNoeW9u/https://media.zenfs.com/en/simply_wall_st__316/a2df42ed0a47d9732f3bf156a253b2f7", "width": 140, "height": 140, "tag": "140x140"}]}, "relatedTickers": ["STZ"]}, {"uuid": "0cf9d8a5-c868-30cc-9ac5-959a50908cbb", "title": "5 Stocks to Watch That Recently Hiked Dividends", "publisher": "Zacks", "link": "https://finance.yahoo.com/news/5-stocks-watch-recently-hiked-130801999.html", "providerPublishTime": 1681391281, "type": "STORY", "thumbnail": {"resolutions": [{"url": "https://s.yimg.com/uu/api/res/1.2/k1o569X.VHa5WoDdfvm3IA--~B/aD00Njk7dz05MDA7YXBwaWQ9eXRhY2h5b24-/https://media.zenfs.com/en/zacks.com/4acc462c890120da9a1551f4cfd337cb", "width": 900, "height": 469, "tag": "original"}, {"url": "https://s.yimg.com/uu/api/res/1.2/t10Pgp0Kid4rnh7xFt7HNQ--~B/Zmk9ZmlsbDtoPTE0MDtweW9mZj0wO3c9MTQwO2FwcGlkPXl0YWNoeW9u/https://media.zenfs.com/en/zacks.com/4acc462c890120da9a1551f4cfd337cb", "width": 140, "height": 140, "tag": "140x140"}]}, "relatedTickers": ["STZ", "QCOM", "EME", "GFL", "FUL"]}, {"uuid": "5f1dbfcd-db95-3c72-8780-aad3a8c99ff2", "title": "Constellation Brands CEO: 'Stubborn' inflation is impacting beer industry", "publisher": "Yahoo Finance Video", "link": "https://finance.yahoo.com/video/constellation-brands-ceo-stubborn-inflation-183128958.html", "providerPublishTime": 1681151488, "type": "VIDEO", "thumbnail": {"resolutions": [{"url": "https://s.yimg.com/uu/api/res/1.2/Ugi.JCcXB7quCAiIoX5OZg--~B/aD0xMDgwO3c9MTkyMDthcHBpZD15dGFjaHlvbg--/https://s.yimg.com/os/creatr-uploaded-images/2023-04/d1886d80-d7cd-11ed-bfef-bb2288c78dca", "width": 1920, "height": 1080, "tag": "original"}, {"url": "https://s.yimg.com/uu/api/res/1.2/hESm8jWTEjom_DEJeVUENg--~B/Zmk9ZmlsbDtoPTE0MDtweW9mZj0wO3c9MTQwO2FwcGlkPXl0YWNoeW9u/https://s.yimg.com/os/creatr-uploaded-images/2023-04/d1886d80-d7cd-11ed-bfef-bb2288c78dca", "width": 140, "height": 140, "tag": "140x140"}]}, "relatedTickers": ["STZ"]}, {"uuid": "88411b34-fdf9-3678-a818-1ce35ba4619c", "title": "\u2018We\u2019re pretty well positioned for summer,\u2019  Constellation Brands CEO says", "publisher": "Yahoo Finance Video", "link": "https://finance.yahoo.com/video/options-earnings-season-definitely-drives-144423231.html", "providerPublishTime": 1681137863, "type": "VIDEO", "thumbnail": {"resolutions": [{"url": "https://s.yimg.com/uu/api/res/1.2/S7sAxZT0ngxFY7umZePkAw--~B/aD03MjA7dz0xMjgwO2FwcGlkPXl0YWNoeW9u/https://s.yimg.com/os/creatr-uploaded-images/2023-04/a1bc2710-d7ad-11ed-bfde-70bc31034b50", "width": 1280, "height": 720, "tag": "original"}, {"url": "https://s.yimg.com/uu/api/res/1.2/Eah95lDAT0qNWR02MwoikA--~B/Zmk9ZmlsbDtoPTE0MDtweW9mZj0wO3c9MTQwO2FwcGlkPXl0YWNoeW9u/https://s.yimg.com/os/creatr-uploaded-images/2023-04/a1bc2710-d7ad-11ed-bfde-70bc31034b50", "width": 140, "height": 140, "tag": "140x140"}]}, "relatedTickers": ["STZ"]}, {"uuid": "dac59e2c-305d-394a-aaf7-c37682d6d04a", "title": "Investors Heavily Search Constellation Brands Inc (STZ): Here is What You Need to Know", "publisher": "Zacks", "link": "https://finance.yahoo.com/news/investors-heavily-search-constellation-brands-130001819.html", "providerPublishTime": 1681131601, "type": "STORY", "thumbnail": {"resolutions": [{"url": "https://s.yimg.com/uu/api/res/1.2/HIalcDlt7JZPKSITVlxPuw--~B/aD02MDA7dz05MDA7YXBwaWQ9eXRhY2h5b24-/https://media.zenfs.com/en/zacks.com/c2fdcaac033e049c74f38d188afcc9f9", "width": 900, "height": 600, "tag": "original"}, {"url": "https://s.yimg.com/uu/api/res/1.2/KwglccBRAqiWaro_ZvjSew--~B/Zmk9ZmlsbDtoPTE0MDtweW9mZj0wO3c9MTQwO2FwcGlkPXl0YWNoeW9u/https://media.zenfs.com/en/zacks.com/c2fdcaac033e049c74f38d188afcc9f9", "width": 140, "height": 140, "tag": "140x140"}]}, "relatedTickers": ["STZ"]}, {"uuid": "387eb1a8-3ad4-3955-9290-30e625cb510a", "title": "2 Companies That Boosted Their Stock Dividends This Week", "publisher": "Barrons.com", "link": "https://finance.yahoo.com/m/387eb1a8-3ad4-3955-9290-30e625cb510a/2-companies-that-boosted.html", "providerPublishTime": 1680940800, "type": "STORY", "thumbnail": {"resolutions": [{"url": "https://s.yimg.com/uu/api/res/1.2/wHkioZWFULotjqP.nlx0hQ--~B/aD02NDA7dz0xMjgwO2FwcGlkPXl0YWNoeW9u/https://media.zenfs.com/en/Barrons.com/566037273c95d9e74840220b133b37c8", "width": 1280, "height": 640, "tag": "original"}, {"url": "https://s.yimg.com/uu/api/res/1.2/.TT9.rhBv9e6Irvb_GrEpA--~B/Zmk9ZmlsbDtoPTE0MDtweW9mZj0wO3c9MTQwO2FwcGlkPXl0YWNoeW9u/https://media.zenfs.com/en/Barrons.com/566037273c95d9e74840220b133b37c8", "width": 140, "height": 140, "tag": "140x140"}]}, "relatedTickers": ["^GSPC", "STZ"]}, {"uuid": "f1a7dd3b-b1da-397c-9a8b-68b16276a07d", "title": "Constellation Brands, Inc. (NYSE:STZ) Q4 2023 Earnings Call Transcript", "publisher": "Insider Monkey", "link": "https://finance.yahoo.com/news/constellation-brands-inc-nyse-stz-024610122.html", "providerPublishTime": 1680921970, "type": "STORY", "thumbnail": {"resolutions": [{"url": "https://s.yimg.com/uu/api/res/1.2/mwGCjqopd0OAv8Ef3jVfSQ--~B/aD01NzY7dz03Njg7YXBwaWQ9eXRhY2h5b24-/https://media.zenfs.com/en/insidermonkey.com/024cf773e2d1163089d4d1a732ceaffa", "width": 768, "height": 576, "tag": "original"}, {"url": "https://s.yimg.com/uu/api/res/1.2/9goPnz_gAVQNkko83i9PJg--~B/Zmk9ZmlsbDtoPTE0MDtweW9mZj0wO3c9MTQwO2FwcGlkPXl0YWNoeW9u/https://media.zenfs.com/en/insidermonkey.com/024cf773e2d1163089d4d1a732ceaffa", "width": 140, "height": 140, "tag": "140x140"}]}, "relatedTickers": ["STZ"]}]}